uplift/__init__.py
uplift/utils.py
uplift_desk-1.1.3.dist-info/METADATA
uplift_desk-1.1.3.dist-info/WHEEL
uplift_desk-1.1.3.dist-info/licenses/LICENSE
uplift_desk-1.1.3.dist-info/RECORD
