Metadata-Version: 2.4
Name: uplift-desk
Version: 1.1.3
Summary: An unofficial Python library for control of Uplift standing desks over BLE
Project-URL: Homepage, https://github.com/Bennett-Wendorf/uplift-desk-controller
Project-URL: Issues, https://github.com/Bennett-Wendorf/uplift-desk-controller/issues
Author-email: Bennett Wendorf <bennett@bennettwendorf.dev>
License-Expression: MIT
License-File: LICENSE
Classifier: Operating System :: OS Independent
Classifier: Programming Language :: Python :: 3
Requires-Python: >=3.8
